LICENSE
MANIFEST.in
README.md
setup.py
jsondatetime/__init__.py
jsondatetime/jsondatetime.py
jsondatetime.egg-info/PKG-INFO
jsondatetime.egg-info/SOURCES.txt
jsondatetime.egg-info/dependency_links.txt
jsondatetime.egg-info/requires.txt
jsondatetime.egg-info/top_level.txt
jsondatetime/tests/__init__.py
jsondatetime/tests/test_jsondatetime.py