Metadata-Version: 2.1
Name: jsondatetime
Version: 0.1.1
Summary: Allows for encoding and decoding of datetime values contained in JSON streams
Home-page: https://github.com/schibsted/json-datetime
Author: Andrew Stribblehill
Author-email: andrew.stribblehill@schibsted.com
License: ISCL
Platform: any
Classifier: Development Status :: 4 - Beta
Classifier: Intended Audience :: Developers
Classifier: License :: OSI Approved :: ISC License (ISCL)
Classifier: Operating System :: OS Independent
Classifier: Programming Language :: Python :: 2.7
Classifier: Programming Language :: Python :: 3
Classifier: Programming Language :: Python :: 3.7
Classifier: Programming Language :: Python :: 3.8
